megatron/energon/__init__.py
megatron/energon/bracecollapse.py
megatron/energon/dataset_config.py
megatron/energon/deprecation.py
megatron/energon/edataclass.py
megatron/energon/errors.py
megatron/energon/eyaml.py
megatron/energon/fork_hook.py
megatron/energon/loader.py
megatron/energon/local_copy.py
megatron/energon/module_loader.py
megatron/energon/retry_stream.py
megatron/energon/rng.py
megatron/energon/sample_utils.py
megatron/energon/savable.py
megatron/energon/savable_loader.py
megatron/energon/source_info.py
megatron/energon/state.py
megatron/energon/typed_converter.py
megatron/energon/watchdog.py
megatron/energon/worker.py
megatron/energon/av/__init__.py
megatron/energon/av/av_data.py
megatron/energon/av/av_decoder.py
megatron/energon/av/av_init.py
megatron/energon/av/utils.py
megatron/energon/av/fastseek/__init__.py
megatron/energon/av/fastseek/fastseek.py
megatron/energon/av/fastseek/keyframeinfo.py
megatron/energon/av/fastseek/reader.py
megatron/energon/av/fastseek/containers/__init__.py
megatron/energon/av/fastseek/containers/matroska.py
megatron/energon/av/fastseek/containers/probe.py
megatron/energon/cache/__init__.py
megatron/energon/cache/base.py
megatron/energon/cache/file_cache_pool.py
megatron/energon/cache/file_store.py
megatron/energon/cache/no_cache.py
megatron/energon/cli/__init__.py
megatron/energon/cli/main.py
megatron/energon/epathlib/__init__.py
megatron/energon/epathlib/epath.py
megatron/energon/epathlib/rclone_config.py
megatron/energon/flavors/__init__.py
megatron/energon/flavors/base_dataset.py
megatron/energon/flavors/captioning.py
megatron/energon/flavors/crude.py
megatron/energon/flavors/image.py
megatron/energon/flavors/image_classification.py
megatron/energon/flavors/interleaved.py
megatron/energon/flavors/multichoice_vqa.py
megatron/energon/flavors/ocr.py
megatron/energon/flavors/similarity_interleaved.py
megatron/energon/flavors/text.py
megatron/energon/flavors/vid_qa.py
megatron/energon/flavors/vqa.py
megatron_energon-7.3.1.dist-info/METADATA
megatron_energon-7.3.1.dist-info/WHEEL
megatron_energon-7.3.1.dist-info/entry_points.txt
megatron_energon-7.3.1.dist-info/licenses/LICENSE
megatron_energon-7.3.1.dist-info/RECORD
